README.md
setup.py
pylooker/__init__.py
pylooker/client.py
pylooker.egg-info/PKG-INFO
pylooker.egg-info/SOURCES.txt
pylooker.egg-info/dependency_links.txt
pylooker.egg-info/requires.txt
pylooker.egg-info/top_level.txt