Metadata-Version: 1.0
Name: pylooker
Version: 0.3.0
Summary: A Python interface to Looker API
Home-page: https://github.com/bufferapp/pylooker
Author: David Gasquez
Author-email: davidgasquez@gmail.com
License: MIT
Keywords: looker
Platform: UNKNOWN
